luma/__init__.py
luma/__main__.py
luma/luma.py
luma_creator-0.0.4.dist-info/METADATA
luma_creator-0.0.4.dist-info/WHEEL
luma_creator-0.0.4.dist-info/entry_points.txt
luma_creator-0.0.4.dist-info/top_level.txt
luma_creator-0.0.4.dist-info/RECORD
